terragpao/__init__.py
ign_terra_gpao-0.0.0.dist-info/METADATA
ign_terra_gpao-0.0.0.dist-info/WHEEL
ign_terra_gpao-0.0.0.dist-info/top_level.txt
ign_terra_gpao-0.0.0.dist-info/RECORD
