Metadata-Version: 2.1
Name: ign-terra-gpao
Version: 0.0.0
Summary: Project use to launch Terra Slave client
Author-email: Guillaume Liegard <guillaume.liegard@ign.fr>
